epi_analyzer/__init__.py
epi_analyzer/detector.py
epi_cli/__init__.py
epi_cli/__main__.py
epi_cli/chat.py
epi_cli/debug.py
epi_cli/keys.py
epi_cli/ls.py
epi_cli/main.py
epi_cli/record.py
epi_cli/run.py
epi_cli/verify.py
epi_cli/view.py
epi_core/__init__.py
epi_core/container.py
epi_core/redactor.py
epi_core/schemas.py
epi_core/serialize.py
epi_core/storage.py
epi_core/trust.py
epi_recorder/__init__.py
epi_recorder/api.py
epi_recorder/async_api.py
epi_recorder/bootstrap.py
epi_recorder/environment.py
epi_recorder/patcher.py
epi_recorder/test_import.py
epi_recorder/test_script.py
epi_recorder-2.2.0.dist-info/licenses/LICENSE
epi_viewer_static/app.js
epi_viewer_static/crypto.js
epi_viewer_static/index.html
epi_viewer_static/viewer_lite.css
epi_recorder-2.2.0.dist-info/METADATA
epi_recorder-2.2.0.dist-info/WHEEL
epi_recorder-2.2.0.dist-info/entry_points.txt
epi_recorder-2.2.0.dist-info/top_level.txt
epi_recorder-2.2.0.dist-info/RECORD
