Metadata-Version: 2.4
Name: epi-recorder
Version: 2.2.0
Summary: The Flight Recorder for AI Agents. Debug LangChain & CrewAI with execution tracing.
Author-email: EPI Labs <mohdibrahim@epilabs.org>
Maintainer-email: Mohd Ibrahim Afridi <mohdibrahim@epilabs.org>
License: Apache-2.0
Project-URL: Homepage, https://epilabs.org
Project-URL: Documentation, https://epilabs.org/docs
Project-URL: Repository, https://github.com/mohdibrahimaiml/epi-recorder
Project-URL: Issues, https://github.com/mohdibrahimaiml/epi-recorder/issues
Project-URL: Discussions, https://github.com/mohdibrahimaiml/epi-recorder/discussions
Keywords: ai,debugging,agents,langchain,crewai,devtools,observability,llm,openai,gemini,tracing,flight-recorder
Classifier: Development Status :: 4 - Beta
Classifier: Intended Audience :: Developers
Classifier: License :: OSI Approved :: Apache Software License
Classifier: Operating System :: OS Independent
Classifier: Programming Language :: Python :: 3
Classifier: Programming Language :: Python :: 3.11
Classifier: Programming Language :: Python :: 3.12
Classifier: Topic :: Software Development :: Debuggers
Classifier: Topic :: Software Development :: Testing
Classifier: Topic :: Scientific/Engineering :: Artificial Intelligence
Classifier: Topic :: System :: Logging
Classifier: Typing :: Typed
Classifier: Framework :: Pydantic
Classifier: Framework :: Pydantic :: 2
Requires-Python: >=3.11
License-File: LICENSE
Requires-Dist: pydantic>=2.0.0
Requires-Dist: cryptography>=41.0.0
Requires-Dist: cbor2>=5.6.0
Requires-Dist: typer[all]>=0.12.0
Requires-Dist: rich>=13.0.0
Requires-Dist: google-generativeai>=0.4.0
Provides-Extra: dev
Requires-Dist: pytest>=8.0.0; extra == "dev"
Requires-Dist: pytest-asyncio>=0.23.0; extra == "dev"
Requires-Dist: pytest-cov>=4.1.0; extra == "dev"
Requires-Dist: black>=24.0.0; extra == "dev"
Requires-Dist: ruff>=0.3.0; extra == "dev"
Dynamic: license-file
